nhelmclient/__init__.py
nhelmclient/main.py
nhelmclient/e2e_tests/__init__.py
nhelmclient/e2e_tests/test_main.py
nhelmclient-0.1.0.dist-info/METADATA
nhelmclient-0.1.0.dist-info/WHEEL
nhelmclient-0.1.0.dist-info/top_level.txt
nhelmclient-0.1.0.dist-info/RECORD
