Metadata-Version: 2.1
Name: nhelmclient
Version: 0.1.0
Summary: Helm client library
Home-page: UNKNOWN
Author: NMachine
License: UNKNOWN
Platform: UNKNOWN
Classifier: Programming Language :: Python :: 3
Classifier: License :: OSI Approved :: MIT License
Classifier: Operating System :: OS Independent
Requires-Python: >=3.6
Requires-Dist: inflection
Requires-Dist: pyyaml
Requires-Dist: typing-extensions
